project/upgrade/rtl/fp4_mul_lut.sv
/*
 * fp4_mul_lut.sv -- FP4 E2M1 multiplication LUT (auto-generated)
 *
 * Input:  a[3:0] FP4 E2M1, b[3:0] FP4 E2M1
 * Output: result[31:0] FP32 IEEE 754 product
 *
 * Generated by gen_fp4_lut.py
 * Author: Vamsidhar Reddy Eraganeni
 * Course: ECE 510 Spring 2026, Portland State University
 */

module fp4_mul_lut (
    input  logic [3:0]  a,
    input  logic [3:0]  b,
    output logic [31:0] result
);

    // 256-entry ROM: index = {a[3:0], b[3:0]}
    // Each entry is the FP32 IEEE 754 encoding of a*b
    logic [31:0] lut [0:255];

    always_comb begin
        case ({a, b})
            8'h00: result = 32'h00000000;  //   0.0 x   0.0 =   0.0000
            8'h01: result = 32'h00000000;  //   0.0 x   0.5 =   0.0000
            8'h02: result = 32'h00000000;  //   0.0 x   1.0 =   0.0000
            8'h03: result = 32'h00000000;  //   0.0 x   1.5 =   0.0000
            8'h04: result = 32'h00000000;  //   0.0 x   2.0 =   0.0000
            8'h05: result = 32'h00000000;  //   0.0 x   3.0 =   0.0000
            8'h06: result = 32'h00000000;  //   0.0 x   4.0 =   0.0000
            8'h07: result = 32'h00000000;  //   0.0 x   6.0 =   0.0000
            8'h08: result = 32'h80000000;  //   0.0 x  -0.0 =  -0.0000
            8'h09: result = 32'h80000000;  //   0.0 x  -0.5 =  -0.0000
            8'h0A: result = 32'h80000000;  //   0.0 x  -1.0 =  -0.0000
            8'h0B: result = 32'h80000000;  //   0.0 x  -1.5 =  -0.0000
            8'h0C: result = 32'h80000000;  //   0.0 x  -2.0 =  -0.0000
            8'h0D: result = 32'h80000000;  //   0.0 x  -3.0 =  -0.0000
            8'h0E: result = 32'h80000000;  //   0.0 x  -4.0 =  -0.0000
            8'h0F: result = 32'h80000000;  //   0.0 x  -6.0 =  -0.0000
            8'h10: result = 32'h00000000;  //   0.5 x   0.0 =   0.0000
            8'h11: result = 32'h3E800000;  //   0.5 x   0.5 =   0.2500
            8'h12: result = 32'h3F000000;  //   0.5 x   1.0 =   0.5000
            8'h13: result = 32'h3F400000;  //   0.5 x   1.5 =   0.7500
            8'h14: result = 32'h3F800000;  //   0.5 x   2.0 =   1.0000
            8'h15: result = 32'h3FC00000;  //   0.5 x   3.0 =   1.5000
            8'h16: result = 32'h40000000;  //   0.5 x   4.0 =   2.0000
            8'h17: result = 32'h40400000;  //   0.5 x   6.0 =   3.0000
            8'h18: result = 32'h80000000;  //   0.5 x  -0.0 =  -0.0000
            8'h19: result = 32'hBE800000;  //   0.5 x  -0.5 =  -0.2500
            8'h1A: result = 32'hBF000000;  //   0.5 x  -1.0 =  -0.5000
            8'h1B: result = 32'hBF400000;  //   0.5 x  -1.5 =  -0.7500
            8'h1C: result = 32'hBF800000;  //   0.5 x  -2.0 =  -1.0000
            8'h1D: result = 32'hBFC00000;  //   0.5 x  -3.0 =  -1.5000
            8'h1E: result = 32'hC0000000;  //   0.5 x  -4.0 =  -2.0000
            8'h1F: result = 32'hC0400000;  //   0.5 x  -6.0 =  -3.0000
            8'h20: result = 32'h00000000;  //   1.0 x   0.0 =   0.0000
            8'h21: result = 32'h3F000000;  //   1.0 x   0.5 =   0.5000
            8'h22: result = 32'h3F800000;  //   1.0 x   1.0 =   1.0000
            8'h23: result = 32'h3FC00000;  //   1.0 x   1.5 =   1.5000
            8'h24: result = 32'h40000000;  //   1.0 x   2.0 =   2.0000
            8'h25: result = 32'h40400000;  //   1.0 x   3.0 =   3.0000
            8'h26: result = 32'h40800000;  //   1.0 x   4.0 =   4.0000
            8'h27: result = 32'h40C00000;  //   1.0 x   6.0 =   6.0000
            8'h28: result = 32'h80000000;  //   1.0 x  -0.0 =  -0.0000
            8'h29: result = 32'hBF000000;  //   1.0 x  -0.5 =  -0.5000
            8'h2A: result = 32'hBF800000;  //   1.0 x  -1.0 =  -1.0000
            8'h2B: result = 32'hBFC00000;  //   1.0 x  -1.5 =  -1.5000
            8'h2C: result = 32'hC0000000;  //   1.0 x  -2.0 =  -2.0000
            8'h2D: result = 32'hC0400000;  //   1.0 x  -3.0 =  -3.0000
            8'h2E: result = 32'hC0800000;  //   1.0 x  -4.0 =  -4.0000
            8'h2F: result = 32'hC0C00000;  //   1.0 x  -6.0 =  -6.0000
            8'h30: result = 32'h00000000;  //   1.5 x   0.0 =   0.0000
            8'h31: result = 32'h3F400000;  //   1.5 x   0.5 =   0.7500
            8'h32: result = 32'h3FC00000;  //   1.5 x   1.0 =   1.5000
            8'h33: result = 32'h40100000;  //   1.5 x   1.5 =   2.2500
            8'h34: result = 32'h40400000;  //   1.5 x   2.0 =   3.0000
            8'h35: result = 32'h40900000;  //   1.5 x   3.0 =   4.5000
            8'h36: result = 32'h40C00000;  //   1.5 x   4.0 =   6.0000
            8'h37: result = 32'h41100000;  //   1.5 x   6.0 =   9.0000
            8'h38: result = 32'h80000000;  //   1.5 x  -0.0 =  -0.0000
            8'h39: result = 32'hBF400000;  //   1.5 x  -0.5 =  -0.7500
            8'h3A: result = 32'hBFC00000;  //   1.5 x  -1.0 =  -1.5000
            8'h3B: result = 32'hC0100000;  //   1.5 x  -1.5 =  -2.2500
            8'h3C: result = 32'hC0400000;  //   1.5 x  -2.0 =  -3.0000
            8'h3D: result = 32'hC0900000;  //   1.5 x  -3.0 =  -4.5000
            8'h3E: result = 32'hC0C00000;  //   1.5 x  -4.0 =  -6.0000
            8'h3F: result = 32'hC1100000;  //   1.5 x  -6.0 =  -9.0000
            8'h40: result = 32'h00000000;  //   2.0 x   0.0 =   0.0000
            8'h41: result = 32'h3F800000;  //   2.0 x   0.5 =   1.0000
            8'h42: result = 32'h40000000;  //   2.0 x   1.0 =   2.0000
            8'h43: result = 32'h40400000;  //   2.0 x   1.5 =   3.0000
            8'h44: result = 32'h40800000;  //   2.0 x   2.0 =   4.0000
            8'h45: result = 32'h40C00000;  //   2.0 x   3.0 =   6.0000
            8'h46: result = 32'h41000000;  //   2.0 x   4.0 =   8.0000
            8'h47: result = 32'h41400000;  //   2.0 x   6.0 =  12.0000
            8'h48: result = 32'h80000000;  //   2.0 x  -0.0 =  -0.0000
            8'h49: result = 32'hBF800000;  //   2.0 x  -0.5 =  -1.0000
            8'h4A: result = 32'hC0000000;  //   2.0 x  -1.0 =  -2.0000
            8'h4B: result = 32'hC0400000;  //   2.0 x  -1.5 =  -3.0000
            8'h4C: result = 32'hC0800000;  //   2.0 x  -2.0 =  -4.0000
            8'h4D: result = 32'hC0C00000;  //   2.0 x  -3.0 =  -6.0000
            8'h4E: result = 32'hC1000000;  //   2.0 x  -4.0 =  -8.0000
            8'h4F: result = 32'hC1400000;  //   2.0 x  -6.0 = -12.0000
            8'h50: result = 32'h00000000;  //   3.0 x   0.0 =   0.0000
            8'h51: result = 32'h3FC00000;  //   3.0 x   0.5 =   1.5000
            8'h52: result = 32'h40400000;  //   3.0 x   1.0 =   3.0000
            8'h53: result = 32'h40900000;  //   3.0 x   1.5 =   4.5000
            8'h54: result = 32'h40C00000;  //   3.0 x   2.0 =   6.0000
            8'h55: result = 32'h41100000;  //   3.0 x   3.0 =   9.0000
            8'h56: result = 32'h41400000;  //   3.0 x   4.0 =  12.0000
            8'h57: result = 32'h41900000;  //   3.0 x   6.0 =  18.0000
            8'h58: result = 32'h80000000;  //   3.0 x  -0.0 =  -0.0000
            8'h59: result = 32'hBFC00000;  //   3.0 x  -0.5 =  -1.5000
            8'h5A: result = 32'hC0400000;  //   3.0 x  -1.0 =  -3.0000
            8'h5B: result = 32'hC0900000;  //   3.0 x  -1.5 =  -4.5000
            8'h5C: result = 32'hC0C00000;  //   3.0 x  -2.0 =  -6.0000
            8'h5D: result = 32'hC1100000;  //   3.0 x  -3.0 =  -9.0000
            8'h5E: result = 32'hC1400000;  //   3.0 x  -4.0 = -12.0000
            8'h5F: result = 32'hC1900000;  //   3.0 x  -6.0 = -18.0000
            8'h60: result = 32'h00000000;  //   4.0 x   0.0 =   0.0000
            8'h61: result = 32'h40000000;  //   4.0 x   0.5 =   2.0000
            8'h62: result = 32'h40800000;  //   4.0 x   1.0 =   4.0000
            8'h63: result = 32'h40C00000;  //   4.0 x   1.5 =   6.0000
            8'h64: result = 32'h41000000;  //   4.0 x   2.0 =   8.0000
            8'h65: result = 32'h41400000;  //   4.0 x   3.0 =  12.0000
            8'h66: result = 32'h41800000;  //   4.0 x   4.0 =  16.0000
            8'h67: result = 32'h41C00000;  //   4.0 x   6.0 =  24.0000
            8'h68: result = 32'h80000000;  //   4.0 x  -0.0 =  -0.0000
            8'h69: result = 32'hC0000000;  //   4.0 x  -0.5 =  -2.0000
            8'h6A: result = 32'hC0800000;  //   4.0 x  -1.0 =  -4.0000
            8'h6B: result = 32'hC0C00000;  //   4.0 x  -1.5 =  -6.0000
            8'h6C: result = 32'hC1000000;  //   4.0 x  -2.0 =  -8.0000
            8'h6D: result = 32'hC1400000;  //   4.0 x  -3.0 = -12.0000
            8'h6E: result = 32'hC1800000;  //   4.0 x  -4.0 = -16.0000
            8'h6F: result = 32'hC1C00000;  //   4.0 x  -6.0 = -24.0000
            8'h70: result = 32'h00000000;  //   6.0 x   0.0 =   0.0000
            8'h71: result = 32'h40400000;  //   6.0 x   0.5 =   3.0000
            8'h72: result = 32'h40C00000;  //   6.0 x   1.0 =   6.0000
            8'h73: result = 32'h41100000;  //   6.0 x   1.5 =   9.0000
            8'h74: result = 32'h41400000;  //   6.0 x   2.0 =  12.0000
            8'h75: result = 32'h41900000;  //   6.0 x   3.0 =  18.0000
            8'h76: result = 32'h41C00000;  //   6.0 x   4.0 =  24.0000
            8'h77: result = 32'h42100000;  //   6.0 x   6.0 =  36.0000
            8'h78: result = 32'h80000000;  //   6.0 x  -0.0 =  -0.0000
            8'h79: result = 32'hC0400000;  //   6.0 x  -0.5 =  -3.0000
            8'h7A: result = 32'hC0C00000;  //   6.0 x  -1.0 =  -6.0000
            8'h7B: result = 32'hC1100000;  //   6.0 x  -1.5 =  -9.0000
            8'h7C: result = 32'hC1400000;  //   6.0 x  -2.0 = -12.0000
            8'h7D: result = 32'hC1900000;  //   6.0 x  -3.0 = -18.0000
            8'h7E: result = 32'hC1C00000;  //   6.0 x  -4.0 = -24.0000
            8'h7F: result = 32'hC2100000;  //   6.0 x  -6.0 = -36.0000
            8'h80: result = 32'h80000000;  //  -0.0 x   0.0 =  -0.0000
            8'h81: result = 32'h80000000;  //  -0.0 x   0.5 =  -0.0000
            8'h82: result = 32'h80000000;  //  -0.0 x   1.0 =  -0.0000
            8'h83: result = 32'h80000000;  //  -0.0 x   1.5 =  -0.0000
            8'h84: result = 32'h80000000;  //  -0.0 x   2.0 =  -0.0000
            8'h85: result = 32'h80000000;  //  -0.0 x   3.0 =  -0.0000
            8'h86: result = 32'h80000000;  //  -0.0 x   4.0 =  -0.0000
            8'h87: result = 32'h80000000;  //  -0.0 x   6.0 =  -0.0000
            8'h88: result = 32'h00000000;  //  -0.0 x  -0.0 =   0.0000
            8'h89: result = 32'h00000000;  //  -0.0 x  -0.5 =   0.0000
            8'h8A: result = 32'h00000000;  //  -0.0 x  -1.0 =   0.0000
            8'h8B: result = 32'h00000000;  //  -0.0 x  -1.5 =   0.0000
            8'h8C: result = 32'h00000000;  //  -0.0 x  -2.0 =   0.0000
            8'h8D: result = 32'h00000000;  //  -0.0 x  -3.0 =   0.0000
            8'h8E: result = 32'h00000000;  //  -0.0 x  -4.0 =   0.0000
            8'h8F: result = 32'h00000000;  //  -0.0 x  -6.0 =   0.0000
            8'h90: result = 32'h80000000;  //  -0.5 x   0.0 =  -0.0000
            8'h91: result = 32'hBE800000;  //  -0.5 x   0.5 =  -0.2500
            8'h92: result = 32'hBF000000;  //  -0.5 x   1.0 =  -0.5000
            8'h93: result = 32'hBF400000;  //  -0.5 x   1.5 =  -0.7500
            8'h94: result = 32'hBF800000;  //  -0.5 x   2.0 =  -1.0000
            8'h95: result = 32'hBFC00000;  //  -0.5 x   3.0 =  -1.5000
            8'h96: result = 32'hC0000000;  //  -0.5 x   4.0 =  -2.0000
            8'h97: result = 32'hC0400000;  //  -0.5 x   6.0 =  -3.0000
            8'h98: result = 32'h00000000;  //  -0.5 x  -0.0 =   0.0000
            8'h99: result = 32'h3E800000;  //  -0.5 x  -0.5 =   0.2500
            8'h9A: result = 32'h3F000000;  //  -0.5 x  -1.0 =   0.5000
            8'h9B: result = 32'h3F400000;  //  -0.5 x  -1.5 =   0.7500
            8'h9C: result = 32'h3F800000;  //  -0.5 x  -2.0 =   1.0000
            8'h9D: result = 32'h3FC00000;  //  -0.5 x  -3.0 =   1.5000
            8'h9E: result = 32'h40000000;  //  -0.5 x  -4.0 =   2.0000
            8'h9F: result = 32'h40400000;  //  -0.5 x  -6.0 =   3.0000
            8'hA0: result = 32'h80000000;  //  -1.0 x   0.0 =  -0.0000
            8'hA1: result = 32'hBF000000;  //  -1.0 x   0.5 =  -0.5000
            8'hA2: result = 32'hBF800000;  //  -1.0 x   1.0 =  -1.0000
            8'hA3: result = 32'hBFC00000;  //  -1.0 x   1.5 =  -1.5000
            8'hA4: result = 32'hC0000000;  //  -1.0 x   2.0 =  -2.0000
            8'hA5: result = 32'hC0400000;  //  -1.0 x   3.0 =  -3.0000
            8'hA6: result = 32'hC0800000;  //  -1.0 x   4.0 =  -4.0000
            8'hA7: result = 32'hC0C00000;  //  -1.0 x   6.0 =  -6.0000
            8'hA8: result = 32'h00000000;  //  -1.0 x  -0.0 =   0.0000
            8'hA9: result = 32'h3F000000;  //  -1.0 x  -0.5 =   0.5000
            8'hAA: result = 32'h3F800000;  //  -1.0 x  -1.0 =   1.0000
            8'hAB: result = 32'h3FC00000;  //  -1.0 x  -1.5 =   1.5000
            8'hAC: result = 32'h40000000;  //  -1.0 x  -2.0 =   2.0000
            8'hAD: result = 32'h40400000;  //  -1.0 x  -3.0 =   3.0000
            8'hAE: result = 32'h40800000;  //  -1.0 x  -4.0 =   4.0000
            8'hAF: result = 32'h40C00000;  //  -1.0 x  -6.0 =   6.0000
            8'hB0: result = 32'h80000000;  //  -1.5 x   0.0 =  -0.0000
            8'hB1: result = 32'hBF400000;  //  -1.5 x   0.5 =  -0.7500
            8'hB2: result = 32'hBFC00000;  //  -1.5 x   1.0 =  -1.5000
            8'hB3: result = 32'hC0100000;  //  -1.5 x   1.5 =  -2.2500
            8'hB4: result = 32'hC0400000;  //  -1.5 x   2.0 =  -3.0000
            8'hB5: result = 32'hC0900000;  //  -1.5 x   3.0 =  -4.5000
            8'hB6: result = 32'hC0C00000;  //  -1.5 x   4.0 =  -6.0000
            8'hB7: result = 32'hC1100000;  //  -1.5 x   6.0 =  -9.0000
            8'hB8: result = 32'h00000000;  //  -1.5 x  -0.0 =   0.0000
            8'hB9: result = 32'h3F400000;  //  -1.5 x  -0.5 =   0.7500
            8'hBA: result = 32'h3FC00000;  //  -1.5 x  -1.0 =   1.5000
            8'hBB: result = 32'h40100000;  //  -1.5 x  -1.5 =   2.2500
            8'hBC: result = 32'h40400000;  //  -1.5 x  -2.0 =   3.0000
            8'hBD: result = 32'h40900000;  //  -1.5 x  -3.0 =   4.5000
            8'hBE: result = 32'h40C00000;  //  -1.5 x  -4.0 =   6.0000
            8'hBF: result = 32'h41100000;  //  -1.5 x  -6.0 =   9.0000
            8'hC0: result = 32'h80000000;  //  -2.0 x   0.0 =  -0.0000
            8'hC1: result = 32'hBF800000;  //  -2.0 x   0.5 =  -1.0000
            8'hC2: result = 32'hC0000000;  //  -2.0 x   1.0 =  -2.0000
            8'hC3: result = 32'hC0400000;  //  -2.0 x   1.5 =  -3.0000
            8'hC4: result = 32'hC0800000;  //  -2.0 x   2.0 =  -4.0000
            8'hC5: result = 32'hC0C00000;  //  -2.0 x   3.0 =  -6.0000
            8'hC6: result = 32'hC1000000;  //  -2.0 x   4.0 =  -8.0000
            8'hC7: result = 32'hC1400000;  //  -2.0 x   6.0 = -12.0000
            8'hC8: result = 32'h00000000;  //  -2.0 x  -0.0 =   0.0000
            8'hC9: result = 32'h3F800000;  //  -2.0 x  -0.5 =   1.0000
            8'hCA: result = 32'h40000000;  //  -2.0 x  -1.0 =   2.0000
            8'hCB: result = 32'h40400000;  //  -2.0 x  -1.5 =   3.0000
            8'hCC: result = 32'h40800000;  //  -2.0 x  -2.0 =   4.0000
            8'hCD: result = 32'h40C00000;  //  -2.0 x  -3.0 =   6.0000
            8'hCE: result = 32'h41000000;  //  -2.0 x  -4.0 =   8.0000
            8'hCF: result = 32'h41400000;  //  -2.0 x  -6.0 =  12.0000
            8'hD0: result = 32'h80000000;  //  -3.0 x   0.0 =  -0.0000
            8'hD1: result = 32'hBFC00000;  //  -3.0 x   0.5 =  -1.5000
            8'hD2: result = 32'hC0400000;  //  -3.0 x   1.0 =  -3.0000
            8'hD3: result = 32'hC0900000;  //  -3.0 x   1.5 =  -4.5000
            8'hD4: result = 32'hC0C00000;  //  -3.0 x   2.0 =  -6.0000
            8'hD5: result = 32'hC1100000;  //  -3.0 x   3.0 =  -9.0000
            8'hD6: result = 32'hC1400000;  //  -3.0 x   4.0 = -12.0000
            8'hD7: result = 32'hC1900000;  //  -3.0 x   6.0 = -18.0000
            8'hD8: result = 32'h00000000;  //  -3.0 x  -0.0 =   0.0000
            8'hD9: result = 32'h3FC00000;  //  -3.0 x  -0.5 =   1.5000
            8'hDA: result = 32'h40400000;  //  -3.0 x  -1.0 =   3.0000
            8'hDB: result = 32'h40900000;  //  -3.0 x  -1.5 =   4.5000
            8'hDC: result = 32'h40C00000;  //  -3.0 x  -2.0 =   6.0000
            8'hDD: result = 32'h41100000;  //  -3.0 x  -3.0 =   9.0000
            8'hDE: result = 32'h41400000;  //  -3.0 x  -4.0 =  12.0000
            8'hDF: result = 32'h41900000;  //  -3.0 x  -6.0 =  18.0000
            8'hE0: result = 32'h80000000;  //  -4.0 x   0.0 =  -0.0000
            8'hE1: result = 32'hC0000000;  //  -4.0 x   0.5 =  -2.0000
            8'hE2: result = 32'hC0800000;  //  -4.0 x   1.0 =  -4.0000
            8'hE3: result = 32'hC0C00000;  //  -4.0 x   1.5 =  -6.0000
            8'hE4: result = 32'hC1000000;  //  -4.0 x   2.0 =  -8.0000
            8'hE5: result = 32'hC1400000;  //  -4.0 x   3.0 = -12.0000
            8'hE6: result = 32'hC1800000;  //  -4.0 x   4.0 = -16.0000
            8'hE7: result = 32'hC1C00000;  //  -4.0 x   6.0 = -24.0000
            8'hE8: result = 32'h00000000;  //  -4.0 x  -0.0 =   0.0000
            8'hE9: result = 32'h40000000;  //  -4.0 x  -0.5 =   2.0000
            8'hEA: result = 32'h40800000;  //  -4.0 x  -1.0 =   4.0000
            8'hEB: result = 32'h40C00000;  //  -4.0 x  -1.5 =   6.0000
            8'hEC: result = 32'h41000000;  //  -4.0 x  -2.0 =   8.0000
            8'hED: result = 32'h41400000;  //  -4.0 x  -3.0 =  12.0000
            8'hEE: result = 32'h41800000;  //  -4.0 x  -4.0 =  16.0000
            8'hEF: result = 32'h41C00000;  //  -4.0 x  -6.0 =  24.0000
            8'hF0: result = 32'h80000000;  //  -6.0 x   0.0 =  -0.0000
            8'hF1: result = 32'hC0400000;  //  -6.0 x   0.5 =  -3.0000
            8'hF2: result = 32'hC0C00000;  //  -6.0 x   1.0 =  -6.0000
            8'hF3: result = 32'hC1100000;  //  -6.0 x   1.5 =  -9.0000
            8'hF4: result = 32'hC1400000;  //  -6.0 x   2.0 = -12.0000
            8'hF5: result = 32'hC1900000;  //  -6.0 x   3.0 = -18.0000
            8'hF6: result = 32'hC1C00000;  //  -6.0 x   4.0 = -24.0000
            8'hF7: result = 32'hC2100000;  //  -6.0 x   6.0 = -36.0000
            8'hF8: result = 32'h00000000;  //  -6.0 x  -0.0 =   0.0000
            8'hF9: result = 32'h40400000;  //  -6.0 x  -0.5 =   3.0000
            8'hFA: result = 32'h40C00000;  //  -6.0 x  -1.0 =   6.0000
            8'hFB: result = 32'h41100000;  //  -6.0 x  -1.5 =   9.0000
            8'hFC: result = 32'h41400000;  //  -6.0 x  -2.0 =  12.0000
            8'hFD: result = 32'h41900000;  //  -6.0 x  -3.0 =  18.0000
            8'hFE: result = 32'h41C00000;  //  -6.0 x  -4.0 =  24.0000
            8'hFF: result = 32'h42100000;  //  -6.0 x  -6.0 =  36.0000
            default: result = 32'h00000000;
        endcase
    end

endmodule

project/m4/src/fp4_mul.sv
/*
 * fp4_mul.sv -- FP4 E2M1 Multiplier with registered output
 *
 * Wraps fp4_mul_lut.sv (combinational 256-entry ROM) and adds a
 * registered output stage for pipeline timing.
 *
 * FP4 E2M1 format (4 bits):
 *   bit 3:   sign
 *   bit 2-1: exponent (2 bits, bias=1)
 *   bit 0:   mantissa (1 bit, implicit leading 1 for normal numbers)
 *
 * Representable values:
 *   Positive: 0.0, 0.5, 1.0, 1.5, 2.0, 3.0, 4.0, 6.0
 *   Negative: -0.0, -0.5, -1.0, -1.5, -2.0, -3.0, -4.0, -6.0
 *
 * Pipeline: 1 stage (registered output, 1-cycle latency)
 *   Cycle 0: present a, b, valid_in
 *   Cycle 1: result and valid_out are stable
 *
 * Clock domain: single clock (clk), rising-edge triggered
 * Reset: active-low synchronous (rst_n)
 *
 * Ports:
 *   clk       input  1-bit   system clock
 *   rst_n     input  1-bit   active-low synchronous reset
 *   a         input  4-bit   FP4 E2M1 operand A
 *   b         input  4-bit   FP4 E2M1 operand B
 *   valid_in  input  1-bit   high when a and b are valid
 *   result    output 32-bit  FP32 IEEE 754 product a*b
 *   valid_out output 1-bit   high when result is valid (1 cycle after valid_in)
 *
 * Debug: compile with -DDEBUG_FP4MUL for $display traces
 *
 * Author: Vamsidhar Reddy Eraganeni
 * Course: ECE 510 Spring 2026, Portland State University
 */

module fp4_mul (
    input  logic        clk,
    input  logic        rst_n,
    input  logic [3:0]  a,
    input  logic [3:0]  b,
    input  logic        valid_in,
    output logic [31:0] result,
    output logic        valid_out
);

    // -----------------------------------------------------------------------
    // Combinational LUT output
    // -----------------------------------------------------------------------
    logic [31:0] lut_result;

    fp4_mul_lut u_lut (
        .a      (a),
        .b      (b),
        .result (lut_result)
    );

    // -----------------------------------------------------------------------
    // Registered output -- 1-cycle latency
    // -----------------------------------------------------------------------
    always_ff @(posedge clk) begin
        if (!rst_n) begin
            result    <= 32'h0;
            valid_out <= 1'b0;
        end else begin
            result    <= lut_result;
            valid_out <= valid_in;

            `ifdef DEBUG_FP4MUL
            if (valid_in)
                $display("[FP4MUL] a=0x%01h b=0x%01h lut_result=0x%08h at t=%0t",
                         a, b, lut_result, $time);
            `endif
        end
    end

endmodule

project/upgrade_archive/tb/fp4_mul_wave.vcd
$version Generated by VerilatedVcd $end
$timescale 1ps $end
 $scope module TOP $end
  $var wire 1 # clk $end
  $var wire 1 $ rst_n $end
  $var wire 4 % a [3:0] $end
  $var wire 4 & b [3:0] $end
  $var wire 1 ' valid_in $end
  $var wire 32 ( result [31:0] $end
  $var wire 1 ) valid_out $end
  $scope module fp4_mul $end
   $var wire 1 # clk $end
   $var wire 1 $ rst_n $end
   $var wire 4 % a [3:0] $end
   $var wire 4 & b [3:0] $end
   $var wire 1 ' valid_in $end
   $var wire 32 ( result [31:0] $end
   $var wire 1 ) valid_out $end
   $var wire 32 * lut_result [31:0] $end
   $scope module u_lut $end
    $var wire 4 % a [3:0] $end
    $var wire 4 & b [3:0] $end
    $var wire 32 * result [31:0] $end
   $upscope $end
  $upscope $end
 $upscope $end
$enddefinitions $end


#0
0#
0$
b0000 %
b0000 &
0'
b00000000000000000000000000000000 (
0)
b00000000000000000000000000000000 *
#1
1#
#2
0#
#3
1#
#4
0#
1$
#5
1#
#6
0#
1'
#7
1#
1)
#8
0#
b0001 &
#9
1#
#10
0#
b0010 &
#11
1#
#12
0#
b0011 &
#13
1#
#14
0#
b0100 &
#15
1#
#16
0#
b0101 &
#17
1#
#18
0#
b0110 &
#19
1#
#20
0#
b0111 &
#21
1#
#22
0#
b1000 &
b10000000000000000000000000000000 *
#23
1#
b10000000000000000000000000000000 (
#24
0#
b1001 &
#25
1#
#26
0#
b1010 &
#27
1#
#28
0#
b1011 &
#29
1#
#30
0#
b1100 &
#31
1#
#32
0#
b1101 &
#33
1#
#34
0#
b1110 &
#35
1#
#36
0#
b1111 &
#37
1#
#38
0#
b0001 %
b0000 &
b00000000000000000000000000000000 *
#39
1#
b00000000000000000000000000000000 (
#40
0#
b0001 &
b00111110100000000000000000000000 *
#41
1#
b00111110100000000000000000000000 (
#42
0#
b0010 &
b00111111000000000000000000000000 *
#43
1#
b00111111000000000000000000000000 (
#44
0#
b0011 &
b00111111010000000000000000000000 *
#45
1#
b00111111010000000000000000000000 (
#46
0#
b0100 &
b00111111100000000000000000000000 *
#47
1#
b00111111100000000000000000000000 (
#48
0#
b0101 &
b00111111110000000000000000000000 *
#49
1#
b00111111110000000000000000000000 (
#50
0#
b0110 &
b01000000000000000000000000000000 *
#51
1#
b01000000000000000000000000000000 (
#52
0#
b0111 &
b01000000010000000000000000000000 *
#53
1#
b01000000010000000000000000000000 (
#54
0#
b1000 &
b10000000000000000000000000000000 *
#55
1#
b10000000000000000000000000000000 (
#56
0#
b1001 &
b10111110100000000000000000000000 *
#57
1#
b10111110100000000000000000000000 (
#58
0#
b1010 &
b10111111000000000000000000000000 *
#59
1#
b10111111000000000000000000000000 (
#60
0#
b1011 &
b10111111010000000000000000000000 *
#61
1#
b10111111010000000000000000000000 (
#62
0#
b1100 &
b10111111100000000000000000000000 *
#63
1#
b10111111100000000000000000000000 (
#64
0#
b1101 &
b10111111110000000000000000000000 *
#65
1#
b10111111110000000000000000000000 (
#66
0#
b1110 &
b11000000000000000000000000000000 *
#67
1#
b11000000000000000000000000000000 (
#68
0#
b1111 &
b11000000010000000000000000000000 *
#69
1#
b11000000010000000000000000000000 (
#70
0#
b0010 %
b0000 &
b00000000000000000000000000000000 *
#71
1#
b00000000000000000000000000000000 (
#72
0#
b0001 &
b00111111000000000000000000000000 *
#73
1#
b00111111000000000000000000000000 (
#74
0#
b0010 &
b00111111100000000000000000000000 *
#75
1#
b00111111100000000000000000000000 (
#76
0#
b0011 &
b00111111110000000000000000000000 *
#77
1#
b00111111110000000000000000000000 (
#78
0#
b0100 &
b01000000000000000000000000000000 *
#79
1#
b01000000000000000000000000000000 (
#80
0#
b0101 &
b01000000010000000000000000000000 *
#81
1#
b01000000010000000000000000000000 (
#82
0#
b0110 &
b01000000100000000000000000000000 *
#83
1#
b01000000100000000000000000000000 (
#84
0#
b0111 &
b01000000110000000000000000000000 *
#85
1#
b01000000110000000000000000000000 (
#86
0#
b1000 &
b10000000000000000000000000000000 *
#87
1#
b10000000000000000000000000000000 (
#88
0#
b1001 &
b10111111000000000000000000000000 *
#89
1#
b10111111000000000000000000000000 (
#90
0#
b1010 &
b10111111100000000000000000000000 *
#91
1#
b10111111100000000000000000000000 (
#92
0#
b1011 &
b10111111110000000000000000000000 *
#93
1#
b10111111110000000000000000000000 (
#94
0#
b1100 &
b11000000000000000000000000000000 *
#95
1#
b11000000000000000000000000000000 (
#96
0#
b1101 &
b11000000010000000000000000000000 *
#97
1#
b11000000010000000000000000000000 (
#98
0#
b1110 &
b11000000100000000000000000000000 *
#99
1#
b11000000100000000000000000000000 (
#100
0#
b1111 &
b11000000110000000000000000000000 *
#101
1#
b11000000110000000000000000000000 (
#102
0#
b0011 %
b0000 &
b00000000000000000000000000000000 *
#103
1#
b00000000000000000000000000000000 (
#104
0#
b0001 &
b00111111010000000000000000000000 *
#105
1#
b00111111010000000000000000000000 (
#106
0#
b0010 &
b00111111110000000000000000000000 *
#107
1#
b00111111110000000000000000000000 (
#108
0#
b0011 &
b01000000000100000000000000000000 *
#109
1#
b01000000000100000000000000000000 (
#110
0#
b0100 &
b01000000010000000000000000000000 *
#111
1#
b01000000010000000000000000000000 (
#112
0#
b0101 &
b01000000100100000000000000000000 *
#113
1#
b01000000100100000000000000000000 (
#114
0#
b0110 &
b01000000110000000000000000000000 *
#115
1#
b01000000110000000000000000000000 (
#116
0#
b0111 &
b01000001000100000000000000000000 *
#117
1#
b01000001000100000000000000000000 (
#118
0#
b1000 &
b10000000000000000000000000000000 *
#119
1#
b10000000000000000000000000000000 (
#120
0#
b1001 &
b10111111010000000000000000000000 *
#121
1#
b10111111010000000000000000000000 (
#122
0#
b1010 &
b10111111110000000000000000000000 *
#123
1#
b10111111110000000000000000000000 (
#124
0#
b1011 &
b11000000000100000000000000000000 *
#125
1#
b11000000000100000000000000000000 (
#126
0#
b1100 &
b11000000010000000000000000000000 *
#127
1#
b11000000010000000000000000000000 (
#128
0#
b1101 &
b11000000100100000000000000000000 *
#129
1#
b11000000100100000000000000000000 (
#130
0#
b1110 &
b11000000110000000000000000000000 *
#131
1#
b11000000110000000000000000000000 (
#132
0#
b1111 &
b11000001000100000000000000000000 *
#133
1#
b11000001000100000000000000000000 (
#134
0#
b0100 %
b0000 &
b00000000000000000000000000000000 *
#135
1#
b00000000000000000000000000000000 (
#136
0#
b0001 &
b00111111100000000000000000000000 *
#137
1#
b00111111100000000000000000000000 (
#138
0#
b0010 &
b01000000000000000000000000000000 *
#139
1#
b01000000000000000000000000000000 (
#140
0#
b0011 &
b01000000010000000000000000000000 *
#141
1#
b01000000010000000000000000000000 (
#142
0#
b0100 &
b01000000100000000000000000000000 *
#143
1#
b01000000100000000000000000000000 (
#144
0#
b0101 &
b01000000110000000000000000000000 *
#145
1#
b01000000110000000000000000000000 (
#146
0#
b0110 &
b01000001000000000000000000000000 *
#147
1#
b01000001000000000000000000000000 (
#148
0#
b0111 &
b01000001010000000000000000000000 *
#149
1#
b01000001010000000000000000000000 (
#150
0#
b1000 &
b10000000000000000000000000000000 *
